e:fifo_tb.v
module fifo(
	data_out,
	full,
	empty,
	clk,
	rst,
	data_in,
        write,
        read);

parameter width = 4;
parameter height = 8;
parameter ptr_width = 3;


output [width-1:0] data_out;
output full;
output empty;
input clk;
input rst;
input [width-1:0] data_in;
input write;
input read;

reg [height-1:0] read_ptr, write_ptr;
reg [ptr_width-1:0]diff;
reg [width-1:0] data_out;
reg [width-1:0] memory[height-1:0];
reg empty_r;
reg empty_r_r;
reg full_r;
reg full_r_r;

assign empty = empty_r & ~empty_r_r;
assign full =  full_r & ~full_r_r;



always@(posedge clk or posedge rst)
begin
if(rst)begin
	write_ptr <= 0;
	data_out <= 0;
	read_ptr <= 0;
	diff <= 0;
	empty_r <= 1;
	full_r <= 0;
end
else if(write && !full && !read) begin 
	memory[write_ptr] <= data_in;
	write_ptr <= write_ptr + 1;
	if(diff== height-1)begin
		full_r <=1;
	end else begin
		diff <= diff + 1;
		full_r <= 0;
	end
end
else if(!write && !empty && read)begin
	data_out <= memory[read_ptr];
	read_ptr <= read_ptr + 1;
	if(diff == 0)begin
		empty_r <= 1;
	end else
	begin
	diff <= diff - 1;
	empty_r <= 0;
        end
end
else if (write && read && empty)begin
	memory[write_ptr] <= data_in;
	write_ptr <= write_ptr + 1;
	if(diff == height - 1)begin
		full_r <= 1;
	end else begin
		diff <= diff +1;
		full_r <= 0;
	end
end
else if (write && read && full)begin
	data_out <= memory[read_ptr];
	read_ptr <= read_ptr + 1;
	if(diff == 0)begin
		empty_r <= 1;
	end else begin
		diff <= diff -1;
		empty_r <= 0;
	end
end

else if (write && read && !full && !empty)
begin
	data_out <= memory[read_ptr];
        memory[write_ptr] <= data_in;
	read_ptr <= read_ptr + 1;
	if(diff == 0)begin
		empty_r <= 1;
	end else begin
		diff <= diff -1;
		empty_r <= 0;
	end
	write_ptr <= write_ptr + 1;
	if(diff == height - 1)begin
		full_r <= 1;
		diff <= 0;
	end else begin
		diff <= diff +1;
		full_r <= 0;
	end
end
end

always@(posedge clk)
begin
	if(rst)begin
		full_r_r <= 0;
		empty_r_r <=1; 
	end else begin
		full_r_r <= full_r;
		empty_r_r <= empty_r;
	end
end
endmodule

fifo_tb.v
`timescale 1ns/1ns
module fifo_tb;
parameter width = 4;
parameter height = 8;

wire [width-1:0] data_out;
wire empty, full;
reg [width-1:0] data_in;
reg clk;
reg rst;
reg write, read;
integer i;



fifo #(.width(width), .height(height)) fifo_i(
	.data_out(data_out), .full(full),
	.empty(empty), .read(read),
	.write(write), .clk(clk), .rst(rst),
	.data_in(data_in));

initial
begin
	clk = 0;
	forever #3 clk = ~clk;
end


initial
begin
	#05;rst = 1;
	#12;rst = 0;

end
initial
begin

	#15;  write = 1; read = 0;
	data_in = 0;
	for( i = 0; i<10; i=i+1)
		@(posedge clk) data_in = i;
	#50; write = 0; read = 1;
	#70; read = 0; write = 1; 
	#1;rst = 1;
	#2; rst = 0; write = 1;
	data_in =1;
	#1; data_in =~data_in;
	#5; read = 1; write = 0;
	#30; write = 1; read = 0;
	#50; read = 1; write = 0;
	#60 $finish;
end
initial
begin
	$dumpfile("fifo_tb.vcd");
	$dumpvars();
end

endmodule

fifo_tb.vcd
$date
	Sat Jan 23 17:45:31 2021
$end
$version
	Icarus Verilog
$end
$timescale
	1ns
$end
$scope module fifo_tb $end
$var wire 1 ! full $end
$var wire 1 " empty $end
$var wire 4 # data_out [3:0] $end
$var reg 1 $ clk $end
$var reg 4 % data_in [3:0] $end
$var reg 1 & read $end
$var reg 1 ' rst $end
$var reg 1 ( write $end
$var integer 32 ) i [31:0] $end
$scope module fifo_i $end
$var wire 1 $ clk $end
$var wire 4 * data_in [3:0] $end
$var wire 1 " empty $end
$var wire 1 ! full $end
$var wire 1 & read $end
$var wire 1 ' rst $end
$var wire 1 ( write $end
$var reg 4 + data_out [3:0] $end
$var reg 3 , diff [2:0] $end
$var reg 1 - empty_r $end
$var reg 1 . empty_r_r $end
$var reg 1 / full_r $end
$var reg 1 0 full_r_r $end
$var reg 8 1 read_ptr [7:0] $end
$var reg 8 2 write_ptr [7:0] $end
$upscope $end
$upscope $end
$enddefinitions $end
#0
$dumpvars
bx 2
bx 1
x0
x/
x.
x-
bx ,
bx +
bx *
bx )
x(
x'
x&
bx %
0$
bx #
x"
x!
$end
#3
1$
#5
0!
0/
1-
b0 ,
b0 1
b0 #
b0 +
b0 2
1'
#6
0$
#9
0"
1.
00
1$
#12
0$
#15
1$
b1 )
b0 %
b0 *
0&
1(
#17
0'
#18
0$
#21
b1 ,
b1 2
b10 )
b1 %
b1 *
1$
#24
0$
#27
b10 ,
b10 2
b11 )
b10 %
b10 *
1$
#30
0$
#33
b11 ,
b11 2
b100 )
b11 %
b11 *
1$
#36
0$
#39
b100 ,
b100 2
b101 )
b100 %
b100 *
1$
#42
0$
#45
b101 ,
b101 2
b110 )
b101 %
b101 *
1$
#48
0$
#51
b110 ,
b110 2
b111 )
b110 %
b110 *
1$
#54
0$
#57
b111 ,
b111 2
b1000 )
b111 %
b111 *
1$
#60
0$
#63
1!
1/
b1000 2
b1001 )
b1000 %
b1000 *
1$
#66
0$
#69
0!
10
b1010 )
b1001 %
b1001 *
1$
#72
0$
#75
b1001 2
1$
#78
0$
#81
b1010 2
1$
#84
0$
#87
b1011 2
1$
#90
0$
#93
b1100 2
1$
#96
0$
#99
b1101 2
1$
#102
0$
#105
b1110 2
1$
#108
0$
#111
b1111 2
1$
#114
0$
#117
b10000 2
1$
#119
1&
0(
#120
0$
#123
0-
b110 ,
b1 1
1$
#126
0$
#129
0.
b101 ,
b10 1
b1 #
b1 +
1$
#132
0$
#135
b100 ,
b11 1
b10 #
b10 +
1$
#138
0$
#141
b11 ,
b100 1
b11 #
b11 +
1$
#144
0$
#147
b10 ,
b101 1
b100 #
b100 +
1$
#150
0$
#153
b1 ,
b110 1
b101 #
b101 +
1$
#156
0$
#159
b0 ,
b111 1
b110 #
b110 +
1$
#162
0$
#165
1"
1-
b1000 1
b111 #
b111 +
1$
#168
0$
#171
0"
1.
1$
#174
0$
#177
b1001 1
bx #
bx +
1$
#180
0$
#183
b1010 1
1$
#186
0$
#189
0/
b1 ,
b10001 2
1$
1(
0&
#190
b0 ,
b0 1
b0 #
b0 +
b0 2
1'
#192
b1 %
b1 *
0'
0$
#193
b1110 %
b1110 *
#195
00
b1 ,
b1 2
1$
#198
0$
0(
1&
#201
0-
b0 ,
b1 1
b1110 #
b1110 +
1$
#204
0$
#207
1"
0.
1-
b10 1
b1 #
b1 +
1$
#210
0$
#213
0"
1.
1$
#216
0$
#219
b11 1
b10 #
b10 +
1$
#222
0$
#225
b100 1
b11 #
b11 +
1$
#228
0$
0&
1(
#231
b1 ,
b10 2
1$
#234
0$
#237
b10 ,
b11 2
1$
#240
0$
#243
b11 ,
b100 2
1$
#246
0$
#249
b100 ,
b101 2
1$
#252
0$
#255
b101 ,
b110 2
1$
#258
0$
#261
b110 ,
b111 2
1$
#264
0$
#267
b111 ,
b1000 2
1$
#270
0$
#273
1!
1/
b1001 2
1$
#276
0$
#278
0(
1&
#279
0!
10
0-
b110 ,
b101 1
b1110 #
b1110 +
1$
#282
0$
#285
0.
b101 ,
b110 1
1$
#288
0$
#291
b100 ,
b111 1
1$
#294
0$
#297
b11 ,
b1000 1
1$
#300
0$
#303
b10 ,
b1001 1
bx #
bx +
1$
#306
0$
#309
b1 ,
b1010 1
1$
#312
0$
#315
b0 ,
b1011 1
1$
#318
0$
#321
1"
1-
b1100 1
1$
#324
0$
#327
0"
1.
1$
#330
0$
#333
b1101 1
1$
