fifo.v
module fifo(
	data_out,
	full,
	empthy,
	clk,
	rst,
	data_in,
        write,
        read);

parameter width = 4;
parameter height = 8;


output [width-1:0] data_out;
output full;
output empthy;
input clk;
input rst;
input [width-1:0] data_in;
input write;
input read;

reg [height-1:0] read_ptr, write_ptr;

reg [width-1:0] data_out;
reg [width-1:0] memory[height-1:0];
reg [width-1:0] counter;

assign empthy = (counter == 0 && read && ~write)?1'b1:1'b0;
assign full =   (counter == height && write && ~read)?1'b1:1'b0;



always@(posedge clk or posedge rst)
begin
if(rst)begin
	write_ptr <= 0;
end
else begin
	if(write && counter < height) begin 
	memory[write_ptr] <= data_in;
	write_ptr <= write_ptr + 1;
end
end
end


always@(posedge clk or posedge rst)
begin 
	if(rst)begin
		read_ptr <= 0;
	end else begin
		if( read && counter != 0)begin
			data_out <= memory[read_ptr];
			read_ptr <= read_ptr + 1;
		end
end
end

always@(posedge clk or posedge rst)
begin
	if(rst)begin
		counter <= 0;
	end else begin
		case({write, read})
			2'b10: counter <= counter + 1;
			2'b01: counter <= counter - 1;
			default: counter <= counter;
		endcase
	end
end
endmodule

fifo_tb.v
`timescale 1ns/1ns
module fifo_tb;
parameter width = 4;
parameter height = 8;

wire [width-1:0] data_out;
wire empthy, full;
reg [width-1:0] data_in;
reg clk;
reg rst;
reg write, read;
integer i;



fifo #(.width(width), .height(height)) fifo_i(
.data_out(data_out), .full(full),
.empthy(empthy), .read(read),
.write(write), .clk(clk), .rst(rst),
.data_in(data_in));

initial
begin
	clk = 0;
	forever #3 clk = ~clk;
end

initial
begin
	#1500 $finish;
end

initial
begin
	#10;rst = 1;
	#30;rst = 0;
	#420;rst = 1;
	#460;rst = 0;

end
initial
begin
        data_in = 1;
	for( i = 0; i<5; i=i+1)
@(negedge clk) data_in = data_in + 1;
end
initial
begin

	#15;  write = 1; read = 0;
         #80; write = 0; read = 1;

	#250; read = 0; write = 0;
	#350; read = 0; write = 1;

	#420; write = 1; read = 1;
	#480; write = 0;
end
initial
begin
	$dumpfile("fifo_tb.vcd");
	$dumpvars();
end

endmodule

fifo_tb.vcd
$date
	Fri Jan 22 00:33:52 2021
$end
$version
	Icarus Verilog
$end
$timescale
	1ns
$end
$scope module fifo_tb $end
$var wire 1 ! full $end
$var wire 1 " empthy $end
$var wire 4 # data_out [3:0] $end
$var reg 1 $ clk $end
$var reg 4 % data_in [3:0] $end
$var reg 1 & read $end
$var reg 1 ' rst $end
$var reg 1 ( write $end
$var integer 32 ) i [31:0] $end
$scope module fifo_i $end
$var wire 1 $ clk $end
$var wire 4 * data_in [3:0] $end
$var wire 1 & read $end
$var wire 1 ' rst $end
$var wire 1 ( write $end
$var wire 1 ! full $end
$var wire 1 " empthy $end
$var reg 4 + counter [3:0] $end
$var reg 4 , data_out [3:0] $end
$var reg 8 - read_ptr [7:0] $end
$var reg 8 . write_ptr [7:0] $end
$upscope $end
$upscope $end
$enddefinitions $end
#0
$dumpvars
bx .
bx -
bx ,
bx +
b1 *
b0 )
x(
x'
x&
b1 %
0$
bx #
x"
x!
$end
#3
1$
#6
b1 )
b10 %
b10 *
0$
#9
1$
#10
0!
b0 .
b0 -
b0 +
1'
#12
b10 )
b11 %
b11 *
0$
#15
0"
1$
0&
1(
#18
b11 )
b100 %
b100 *
0$
#21
1$
#24
b100 )
b101 %
b101 *
0$
#27
1$
#30
b101 )
b110 %
b110 *
0$
#33
1$
#36
0$
#39
1$
#40
0'
#42
0$
#45
b1 .
b1 +
1$
#48
0$
#51
b10 +
b10 .
1$
#54
0$
#57
b11 .
b11 +
1$
#60
0$
#63
b100 +
b100 .
1$
#66
0$
#69
b101 .
b101 +
1$
#72
0$
#75
b110 +
b110 .
1$
#78
0$
#81
b111 .
b111 +
1$
#84
0$
#87
1!
b1000 +
b1000 .
1$
#90
0$
#93
0!
b1001 +
1$
#95
1&
0(
#96
0$
#99
b1000 +
b1 -
b110 #
b110 ,
1$
#102
0$
#105
b10 -
b111 +
1$
#108
0$
#111
b110 +
b11 -
1$
#114
0$
#117
b100 -
b101 +
1$
#120
0$
#123
b100 +
b101 -
1$
#126
0$
#129
b110 -
b11 +
1$
#132
0$
#135
b10 +
b111 -
1$
#138
0$
#141
b1000 -
b1 +
1$
#144
0$
#147
1"
b0 +
b1001 -
bx #
bx ,
1$
#150
0$
#153
0"
b1111 +
1$
#156
0$
#159
b1110 +
b1010 -
1$
#162
0$
#165
b1011 -
b1101 +
1$
#168
0$
#171
b1100 +
b1100 -
1$
#174
0$
#177
b1101 -
b1011 +
1$
#180
0$
#183
b1010 +
b1110 -
1$
#186
0$
#189
b1111 -
b1001 +
1$
#192
0$
#195
b1000 +
b10000 -
1$
#198
0$
#201
b10001 -
b111 +
1$
#204
0$
#207
b110 +
b10010 -
1$
#210
0$
#213
b10011 -
b101 +
1$
#216
0$
#219
b100 +
b10100 -
1$
#222
0$
#225
b10101 -
b11 +
1$
#228
0$
#231
b10 +
b10110 -
1$
#234
0$
#237
b10111 -
b1 +
1$
#240
0$
#243
1"
b0 +
b11000 -
1$
#246
0$
#249
0"
b1111 +
1$
#252
0$
#255
b1110 +
b11001 -
1$
#258
0$
#261
b11010 -
b1101 +
1$
#264
0$
#267
b1100 +
b11011 -
1$
#270
0$
#273
b11100 -
b1011 +
1$
#276
0$
#279
b1010 +
b11101 -
1$
#282
0$
#285
b11110 -
b1001 +
1$
#288
0$
#291
b1000 +
b11111 -
1$
#294
0$
#297
b100000 -
b111 +
1$
#300
0$
#303
b110 +
b100001 -
1$
#306
0$
#309
b100010 -
b101 +
1$
#312
0$
#315
b100 +
b100011 -
1$
#318
0$
#321
b100100 -
b11 +
1$
#324
0$
#327
b10 +
b100101 -
1$
#330
0$
#333
b100110 -
b1 +
1$
#336
0$
#339
1"
b0 +
b100111 -
1$
#342
0$
#345
0"
1$
0&
#348
0$
#351
1$
#354
0$
#357
1$
#360
0$
#363
1$
#366
0$
#369
1$
#372
0$
#375
1$
#378
0$
#381
1$
#384
0$
#387
1$
#390
0$
#393
1$
#396
0$
#399
1$
#402
0$
#405
1$
#408
0$
#411
1$
#414
0$
#417
1$
#420
0$
#423
1$
#426
0$
#429
1$
#432
0$
#435
1$
#438
0$
#441
1$
#444
0$
#447
1$
#450
0$
#453
1$
#456
0$
#459
1$
#460
b0 .
b0 -
1'
